imppkg/__init__.py
imppkg/data.json
imppkg/harmonic_mean.c
imppkg/harmonic_mean.pypy39-pp73-win_amd64.pyd
imppkg/harmonic_mean.pyx
imppkg/harmony.py
imppkg/hello.py
imppkg/py.typed
pubpypack_harmony_shivam-0.0.2.dist-info/METADATA
pubpypack_harmony_shivam-0.0.2.dist-info/WHEEL
pubpypack_harmony_shivam-0.0.2.dist-info/entry_points.txt
pubpypack_harmony_shivam-0.0.2.dist-info/top_level.txt
pubpypack_harmony_shivam-0.0.2.dist-info/RECORD
